<?xml version="1.0"?>
<menu>
<header>
	<listname>Shoot- / Working Games</listname>
	<lastlistupdate>05/18/2016</lastlistupdate>
	<listversion>mame 0.171</listversion>
	<exporterversion>r0man0 ahk script</exporterversion>
</header>
<game name="acrobatm" index="" image="">
	<description>Acrobat Mission</description>
	<cloneof/>
	<crc/>
	<manufacturer>UPL (Taito license)</manufacturer>
	<year>1991</year>
	<genre>Shoot-</genre>
	<rating/>
	<enabled>Yes</enabled>
</game>
<game name="agallet" index="" image="">
	<description>Air Gallet (Europe)</description>
	<cloneof/>
	<crc/>
	<manufacturer>Gazelle (Banpresto license)</manufacturer>
	<year>1996</year>
	<genre>Shoot-</genre>
	<rating/>
	<enabled>Yes</enabled>
</game>
<game name="buckrog" index="" image="">
	<description>Buck Rogers: Planet of Zoom</description>
	<cloneof/>
	<crc/>
	<manufacturer>Sega</manufacturer>
	<year>1982</year>
	<genre>Shoot-</genre>
	<rating/>
	<enabled>Yes</enabled>
</game>
<game name="destroyr" index="" image="">
	<description>Destroyer (version O2)</description>
	<cloneof/>
	<crc/>
	<manufacturer>Atari</manufacturer>
	<year>1977</year>
	<genre>Shoot-</genre>
	<rating/>
	<enabled>Yes</enabled>
</game>
<game name="donpachikr" index="" image="">
	<description>DonPachi (Korea)</description>
	<cloneof>donpachi</cloneof>
	<crc/>
	<manufacturer>Cave (Atlus license)</manufacturer>
	<year>1995</year>
	<genre>Shoot-</genre>
	<rating/>
	<enabled>Yes</enabled>
</game>
<game name="fa" index="" image="">
	<description>F/A (Japan)</description>
	<cloneof>fghtatck</cloneof>
	<crc/>
	<manufacturer>Namco</manufacturer>
	<year>1992</year>
	<genre>Shoot-</genre>
	<rating/>
	<enabled>Yes</enabled>
</game>
<game name="gunbirdk" index="" image="">
	<description>Gunbird (Korea)</description>
	<cloneof>gunbird</cloneof>
	<crc/>
	<manufacturer>Psikyo</manufacturer>
	<year>1994</year>
	<genre>Shoot-</genre>
	<rating/>
	<enabled>Yes</enabled>
</game>
<game name="popflame" index="" image="">
	<description>Pop Flamer (protected)</description>
	<cloneof/>
	<crc/>
	<manufacturer>Jaleco</manufacturer>
	<year>1982</year>
	<genre>Shoot-</genre>
	<rating/>
	<enabled>Yes</enabled>
</game>
<game name="roadblst2" index="" image="">
	<description>Road Blasters (upright, rev 2)</description>
	<cloneof>roadblst</cloneof>
	<crc/>
	<manufacturer>Atari Games</manufacturer>
	<year>1987</year>
	<genre>Shoot-</genre>
	<rating/>
	<enabled>Yes</enabled>
</game>
<game name="s1945p" index="" image="">
	<description>Strikers 1945 Plus</description>
	<cloneof/>
	<crc/>
	<manufacturer>Psikyo</manufacturer>
	<year>1999</year>
	<genre>Shoot-</genre>
	<rating/>
	<enabled>Yes</enabled>
</game>
<game name="sdgndmps" index="" image="">
	<description>SD Gundam Psycho Salamander no Kyoui</description>
	<cloneof/>
	<crc/>
	<manufacturer>Banpresto / Bandai</manufacturer>
	<year>1991</year>
	<genre>Shoot-</genre>
	<rating/>
	<enabled>Yes</enabled>
</game>
<game name="skybase" index="" image="">
	<description>Sky Base</description>
	<cloneof/>
	<crc/>
	<manufacturer>Omori Electric Co., Ltd.</manufacturer>
	<year>1982</year>
	<genre>Shoot-</genre>
	<rating/>
	<enabled>Yes</enabled>
</game>
<game name="spacecho" index="" image="">
	<description>Space Echo (set 1)</description>
	<cloneof>speakres</cloneof>
	<crc/>
	<manufacturer>bootleg (Gayton Games)</manufacturer>
	<year>1980</year>
	<genre>Shoot-</genre>
	<rating/>
	<enabled>Yes</enabled>
</game>
<game name="subroc3d" index="" image="">
	<description>Subroc-3D</description>
	<cloneof/>
	<crc/>
	<manufacturer>Sega</manufacturer>
	<year>1982</year>
	<genre>Shoot-</genre>
	<rating/>
	<enabled>Yes</enabled>
</game>
</menu>