<?xml version="1.0"?>
<menu>
<header>
	<listname>Mini-Games / All Games</listname>
	<lastlistupdate>05/18/2016</lastlistupdate>
	<listversion>mame 0.171</listversion>
	<exporterversion>r0man0 ahk script</exporterversion>
</header>
<game name="csclubh" index="" image="">
	<description>Capcom Sports Club (Hispanic 970722)</description>
	<cloneof>csclub</cloneof>
	<crc/>
	<manufacturer>Capcom</manufacturer>
	<year>1997</year>
	<genre>Mini-Games</genre>
	<rating/>
	<enabled>Yes</enabled>
</game>
<game name="ichirjbl" index="" image="">
	<description>Puzzle &amp; Action: Ichidant-R (Japan) (bootleg)</description>
	<cloneof>ichir</cloneof>
	<crc/>
	<manufacturer>bootleg</manufacturer>
	<year>1994</year>
	<genre>Mini-Games</genre>
	<rating/>
	<enabled>Yes</enabled>
</game>
<game name="kotmh" index="" image="">
	<description>King of the Monsters (set 2)</description>
	<cloneof>kotm</cloneof>
	<crc/>
	<manufacturer>SNK</manufacturer>
	<year>1991</year>
	<genre>Mini-Games</genre>
	<rating/>
	<enabled>Yes</enabled>
</game>
</menu>